nonebot_plugin_ollama-0.2.3.dist-info/METADATA
nonebot_plugin_ollama-0.2.3.dist-info/WHEEL
nonebot_plugin_ollama-0.2.3.dist-info/entry_points.txt
nonebot_plugin_ollama-0.2.3.dist-info/licenses/LICENSE
nonebot_plugin_ollama/__init__.py
nonebot_plugin_ollama/config.py
nonebot_plugin_ollama-0.2.3.dist-info/RECORD
