Metadata-Version: 2.1
Name: nonebot-plugin-ollama
Version: 0.2.3
Summary: 通过ollama提供的接口，将你的nonebot连接到本地部署的基于ollama框架的模型
Author-Email: MaStAr <2024381053@mails.szu.edu.cn>
License: MIT
Requires-Python: >=3.9
Requires-Dist: nonebot2>=2.4.0
Requires-Dist: aiohttp>=3.11.10
